regcomp/__init__.py
regcomp/main.py
regcomp/regression_methods/__init__.py
regcomp/regression_methods/elasticnet.py
regcomp/regression_methods/omp.py
regcomp-0.0.7.dist-info/LICENSE.txt
regcomp-0.0.7.dist-info/METADATA
regcomp-0.0.7.dist-info/WHEEL
regcomp-0.0.7.dist-info/top_level.txt
regcomp-0.0.7.dist-info/RECORD
