Metadata-Version: 2.1
Name: regcomp
Version: 0.0.7
Summary: A tool to compare linear regression methods
Home-page: https://github.com/osarwar/RegComp
Author: Owais Sarwar
Author-email: osarwar@andrew.cmu.edu
License: UNKNOWN
Platform: UNKNOWN
Classifier: Programming Language :: Python :: 3
Classifier: License :: OSI Approved :: MIT License
Classifier: Operating System :: OS Independent
Requires-Python: >=3.5
Requires-Dist: pandas (>=1.1.4)
Requires-Dist: numpy (>=1.16.1)
Requires-Dist: scikit-learn (>=0.23.2)
Requires-Dist: matplotlib
